[
  {
    "question": "AI 수요 예측은 언제 실행되나요?",
    "answer": "ORDER101에서는 매주 월요일 새벽 자동으로 다음 12주치 수요 예측이 실행되도록 설정되어 있습니다."
  },
  {
    "question": "스마트 발주는 어떻게 계산되나요?",
    "answer": "AI 수요 예측값과 리드타임, 안전재고 정책을 기반으로 필요 수량 = (예측수요 × 리드타임) + 안전재고 – 현재고 – 입고예정 형태로 계산됩니다."
  },
  {
    "question": "AI 모델은 어떤 데이터를 사용하나요?",
    "answer": "SKU 판매 데이터, 이동평균, 요일/계절성, 카테고리 정보 등을 포함한 약 40여 개의 피처중 상위 5개의 피처를 사용합니다."
  },
  {
    "question": "재학습은 어떻게 동작하나요?",
    "answer": "매월 1일 자동으로 모델 재학습이 실행되며, HQ_ADMIN 사용자는 수동으로도 재학습을 요청할 수 있습니다."
  },
  {
    "question": "AI 예측이 실패하면 어떻게 되나요?",
    "answer": "예측 파이프라인에서 오류가 발생하면 Python AI 서버가 실패 로그를 남기며, Java 서버에도 실패 상태를 반환합니다."
  },
    {
      "question": "AI 수요 예측 주기는 어떻게 되나요?",
      "answer": "일 단위로 예측 모델이 갱신되며, 주간 단위로 스마트 발주에 반영됩니다."
    },
    {
      "question": "예측 모델은 어떤 데이터를 사용하나요?",
      "answer": "과거 판매, 발주, 재고, 프로모션, 요일/계절성, 외부 변수 데이터를 사용합니다."
    },
    {
      "question": "모델 성능은 어디서 확인할 수 있나요?",
      "answer": "AI 리포트에서 MAPE, RMSE 등 평가 지표를 기간별로 확인할 수 있습니다."
    },
    {
      "question": "스마트 발주 추천 수량은 어떻게 계산되나요?",
      "answer": "예측 수요에서 현재고와 입고 예정 수량을 차감하고 안전재고를 고려해 제안 수량을 산출합니다."
    },
    {
      "question": "모델 학습 스케줄을 변경할 수 있나요?",
      "answer": "시스템 설정 > AI 스케줄에서 일자와 시간대를 조정할 수 있습니다."
    },
    {
      "question": "피처 엔지니어링 항목을 커스터마이즈할 수 있나요?",
      "answer": "현재 기본 피처 세트를 사용하며, 추가 피처 반영은 운영팀을 통해 별도 개발이 필요합니다."
    },
    {
      "question": "AI 추천을 무시하고 수동 입력해도 되나요?",
      "answer": "가능하며, 수동 입력 시 변경 이력이 기록되고 추후 모델 개선 피드백으로 활용됩니다."
    },
    {
      "question": "모델 버전 관리는 어떻게 되나요?",
      "answer": "모델 배포 시 버전이 부여되며, AI 리포트에서 각 버전의 성능과 배포 일자를 확인할 수 있습니다."
    },
    {
      "question": "예측 실패 시 어떻게 알림이 오나요?",
      "answer": "모델 학습이나 예측 작업 실패 시 HQ_ADMIN에게 시스템 알림과 메일이 발송됩니다."
    },
    {
      "question": "데이터 품질 검증은 어느 단계에서 하나요?",
      "answer": "ETL 완료 후 결측과 이상치 검증을 수행하며, 문제 발견 시 알림과 리포트로 통보합니다."
    },
    {
      "question": "AI가 발주 승인까지 자동으로 하나요?",
      "answer": "현재는 초안 생성까지 자동화되며, 최종 승인/반려는 HQ_ADMIN이 결정합니다."
    },
    {
      "question": "수요 급증 이벤트는 어떻게 반영되나요?",
      "answer": "프로모션 일정과 외부 이벤트 캘린더를 입력하면 해당 기간 수요 가중치를 적용합니다."
    },
    {
      "question": "모델 학습 데이터 보존 기간은 얼마인가요?",
      "answer": "기본 3년 데이터를 보존하며, 정책에 따라 기간을 변경할 수 있습니다."
    },
    {
      "question": "피크 시즌 대비 기능이 있나요?",
      "answer": "시즌 태그를 지정하면 해당 기간 예측 가중치와 안전재고 상향 규칙이 적용됩니다."
    },
    {
      "question": "AI 결과를 CSV로 받을 수 있나요?",
      "answer": "AI 리포트에서 예측 결과와 추천 발주 수량을 CSV로 다운로드할 수 있습니다."
    },
    {
      "question": "모델 재학습을 수동으로 실행할 수 있나요?",
      "answer": "AI 관리 화면에서 '재학습 실행' 버튼을 눌러 즉시 재학습을 트리거할 수 있습니다."
    },
    {
      "question": "스마트 발주 실패 사유는 어디서 보나요?",
      "answer": "시스템 로그의 AI/발주 섹션에서 실패 코드와 상세 메시지를 확인할 수 있습니다."
    },
    {
      "question": "예측 정확도가 낮을 때 어떻게 대응하나요?",
      "answer": "데이터 누락 여부를 확인하고, 이상치나 품절 기간을 조정한 후 재학습을 수행합니다."
    },
    {
      "question": "AI 기능 권한은 어떻게 관리하나요?",
      "answer": "HQ_ADMIN만 AI 설정 변경과 모델 재학습 실행 권한을 갖습니다."
    },
    {
      "question": "외부 날씨 데이터 연동이 가능한가요?",
      "answer": "기본 연동은 제공하지 않지만, API 키를 등록하면 커스텀 피처로 추가할 수 있습니다."
    },
    {
      "question": "AI 로그는 어느 기간까지 보관되나요?",
      "answer": "기본 90일간 보관하며, 필요 시 로그 보존 기간을 확장할 수 있습니다."
    },
    {
      "question": "추천 수량이 0으로 나오는 이유는 무엇인가요?",
      "answer": "최근 판매나 출고 이력이 없거나 충분한 재고가 있는 경우 0으로 제안될 수 있습니다."
    },
    {
      "question": "AI가 품목 단종을 인지하나요?",
      "answer": "품목 상태가 비활성화로 변경되면 학습과 예측 대상에서 제외됩니다."
    },
    {
      "question": "테스트 환경에서 별도 모델을 사용할 수 있나요?",
      "answer": "스테이징 환경에 테스트 모델을 배포해 운영과 분리된 실험을 진행할 수 있습니다."
    },
    {
      "question": "모델 입력 피처를 추적할 수 있나요?",
      "answer": "피처 로그를 활성화하면 예측 시점의 입력 피처 값을 다운로드할 수 있습니다."
    },
    {
      "question": "AI 권장 발주를 자동 제출하도록 설정할 수 있나요?",
      "answer": "정책 관리에서 '자동 제출'을 켜면 승인 없이 바로 제출되며, HQ_ADMIN만 설정할 수 있습니다."
    },
    {
      "question": "AI 학습 리소스 한도는 어디서 설정하나요?",
      "answer": "시스템 설정 > 리소스 한도에서 GPU/CPU 사용량과 동시 학습 작업 수를 제한할 수 있습니다."
    },
    {
      "question": "모델이 신규 상품을 어떻게 처리하나요?",
      "answer": "신규 상품은 유사 카테고리 평균과 안전재고 규칙을 활용한 콜드스타트 로직을 사용합니다."
    },
    {
      "question": "AI 결과를 가맹점에 직접 노출하나요?",
      "answer": "HQ/HQ_ADMIN 전용으로 제공되며, 가맹점에는 추천 결과가 노출되지 않습니다."
    },
    {
      "question": "실험군/대조군 테스트가 가능한가요?",
      "answer": "A/B 테스트 모듈을 통해 가맹점 그룹별로 다른 추천 전략을 적용할 수 있습니다."
    },
    {
      "question": "예측에 사용되는 프로모션 데이터는 어디서 입력하나요?",
      "answer": "마케팅 캘린더에서 프로모션 일정과 할인율을 입력하면 예측에 반영됩니다."
    },
    {
      "question": "AI 관련 알림을 분리해 받을 수 있나요?",
      "answer": "알림 설정에서 AI 모델과 스케줄 이벤트만 별도로 구독하거나 해제할 수 있습니다."
    },
    {
      "question": "스마트 발주 초안 생성 기준을 수정할 수 있나요?",
      "answer": "정책 관리에서 최소 발주 단위, 안전재고 가중치 등을 조정해 초안 계산 로직에 반영합니다."
    },
    {
      "question": "AI 기능 감사 로그를 제공하나요?",
      "answer": "모델 실행, 설정 변경, 재학습 요청 기록을 감사 로그로 제공하며 HQ_ADMIN만 조회 가능합니다."
    },
    {
      "question": "데이터 파이프라인 장애 시 조치는 어떻게 하나요?",
      "answer": "데이터 수집이나 전처리 실패 시 자동 롤백과 알림이 발송되며, 장애 복구 후 재처리를 수행합니다."
    },
    {
      "question": "AI 모델이 재고 데이터를 직접 수정하나요?",
      "answer": "모델은 재고를 수정하지 않으며, 추천 값만 생성하고 실제 재고 변경은 입출고나 발주 처리에서 이루어집니다."
    }
]
